{"title":"lgbt","id":"42c940d1-9684-4a5f-9fe1-b0104bdabf9c","stickers":[{"body":"1055_gay_man","info":{"mimetype":"image/png","h":93, "w":128,"thumbnail_url":"mxc://matrix.org/vJnDebugwMoVgHJrBHrFjVJs"},"msgtype":"m.sticker","url":"mxc://matrix.org/vJnDebugwMoVgHJrBHrFjVJs" ,"id":"lgbt-1055_gay_man"},{"body":"1509_bigender","info":{"mimetype":"image/png","h":93, "w":128,"thumbnail_url":"mxc://matrix.org/HABAycPiesJxGPFZImqKrKyq"},"msgtype":"m.sticker","url":"mxc://matrix.org/HABAycPiesJxGPFZImqKrKyq" ,"id":"lgbt-1509_bigender"},{"body":"1691_genderfluid","info":{"mimetype":"image/png","h":93, "w":128,"thumbnail_url":"mxc://matrix.org/NYmSjRCFLThKOxIVRTZmfDkN"},"msgtype":"m.sticker","url":"mxc://matrix.org/NYmSjRCFLThKOxIVRTZmfDkN" ,"id":"lgbt-1691_genderfluid"},{"body":"2729_aromantic","info":{"mimetype":"image/png","h":93, "w":128,"thumbnail_url":"mxc://matrix.org/AtsKMnpMthDBJvsvrlUdPzpV"},"msgtype":"m.sticker","url":"mxc://matrix.org/AtsKMnpMthDBJvsvrlUdPzpV" ,"id":"lgbt-2729_aromantic"},{"body":"3043_agender","info":{"mimetype":"image/png","h":93, "w":128,"thumbnail_url":"mxc://matrix.org/FmXCtoKurygicNHCmhExgroF"},"msgtype":"m.sticker","url":"mxc://matrix.org/FmXCtoKurygicNHCmhExgroF" ,"id":"lgbt-3043_agender"},{"body":"3084_demigirl","info":{"mimetype":"image/png","h":93, "w":128,"thumbnail_url":"mxc://matrix.org/PLNfTZzAHRgpWUxkiwhduzMl"},"msgtype":"m.sticker","url":"mxc://matrix.org/PLNfTZzAHRgpWUxkiwhduzMl" ,"id":"lgbt-3084_demigirl"},{"body":"3473_demiboy","info":{"mimetype":"image/png","h":93, "w":128,"thumbnail_url":"mxc://matrix.org/GpXUOkPTBMXGcEOdtWdiHbOt"},"msgtype":"m.sticker","url":"mxc://matrix.org/GpXUOkPTBMXGcEOdtWdiHbOt" ,"id":"lgbt-3473_demiboy"},{"body":"3913_pansexual","info":{"mimetype":"image/png","h":93, "w":128,"thumbnail_url":"mxc://matrix.org/GgRZLBbtabUEcDEXocmkxVEe"},"msgtype":"m.sticker","url":"mxc://matrix.org/GgRZLBbtabUEcDEXocmkxVEe" ,"id":"lgbt-3913_pansexual"},{"body":"4016_nonbinary","info":{"mimetype":"image/png","h":93, "w":128,"thumbnail_url":"mxc://matrix.org/miQuNJJmrjsmCUYPBEFGinSU"},"msgtype":"m.sticker","url":"mxc://matrix.org/miQuNJJmrjsmCUYPBEFGinSU" ,"id":"lgbt-4016_nonbinary"},{"body":"5100_flag_demisexual","info":{"mimetype":"image/png","h":120, "w":128,"thumbnail_url":"mxc://matrix.org/pzszMPUDEGGdjpiUCMemfwhT"},"msgtype":"m.sticker","url":"mxc://matrix.org/pzszMPUDEGGdjpiUCMemfwhT" ,"id":"lgbt-5100_flag_demisexual"},{"body":"5612_genderqueer","info":{"mimetype":"image/png","h":93, "w":128,"thumbnail_url":"mxc://matrix.org/fUntDcdQMPnEAACFKuUivpgJ"},"msgtype":"m.sticker","url":"mxc://matrix.org/fUntDcdQMPnEAACFKuUivpgJ" ,"id":"lgbt-5612_genderqueer"},{"body":"6130_lesbian","info":{"mimetype":"image/png","h":93, "w":128,"thumbnail_url":"mxc://matrix.org/JdUclVWOjLeMjxPFcEeSmMMi"},"msgtype":"m.sticker","url":"mxc://matrix.org/JdUclVWOjLeMjxPFcEeSmMMi" ,"id":"lgbt-6130_lesbian"},{"body":"6153_bisexual","info":{"mimetype":"image/png","h":93, "w":128,"thumbnail_url":"mxc://matrix.org/jfyHsTDShSzsPjJGCdFhggXb"},"msgtype":"m.sticker","url":"mxc://matrix.org/jfyHsTDShSzsPjJGCdFhggXb" ,"id":"lgbt-6153_bisexual"},{"body":"6612_graygender","info":{"mimetype":"image/png","h":93, "w":128,"thumbnail_url":"mxc://matrix.org/YHOJivBFwaGczyZyXKZNHgdV"},"msgtype":"m.sticker","url":"mxc://matrix.org/YHOJivBFwaGczyZyXKZNHgdV" ,"id":"lgbt-6612_graygender"},{"body":"7566_grayace","info":{"mimetype":"image/png","h":93, "w":128,"thumbnail_url":"mxc://matrix.org/FWwGLjrxNloapLRaOBumBPaM"},"msgtype":"m.sticker","url":"mxc://matrix.org/FWwGLjrxNloapLRaOBumBPaM" ,"id":"lgbt-7566_grayace"},{"body":"8003_grayaroace","info":{"mimetype":"image/png","h":93, "w":128,"thumbnail_url":"mxc://matrix.org/rpMPuEITzBJsIUmlsnbZZAyI"},"msgtype":"m.sticker","url":"mxc://matrix.org/rpMPuEITzBJsIUmlsnbZZAyI" ,"id":"lgbt-8003_grayaroace"},{"body":"8096_grayaro","info":{"mimetype":"image/png","h":93, "w":128,"thumbnail_url":"mxc://matrix.org/nTGYpSTpjuzVtxbdbaqOGrXx"},"msgtype":"m.sticker","url":"mxc://matrix.org/nTGYpSTpjuzVtxbdbaqOGrXx" ,"id":"lgbt-8096_grayaro"},{"body":"8645_polysexual","info":{"mimetype":"image/png","h":93, "w":128,"thumbnail_url":"mxc://matrix.org/cLBIGfbKJQBKajwuembjPfIl"},"msgtype":"m.sticker","url":"mxc://matrix.org/cLBIGfbKJQBKajwuembjPfIl" ,"id":"lgbt-8645_polysexual"},{"body":"9250_demigender","info":{"mimetype":"image/png","h":93, "w":128,"thumbnail_url":"mxc://matrix.org/eKxKVeetWKJIWeSzPhyGQDtW"},"msgtype":"m.sticker","url":"mxc://matrix.org/eKxKVeetWKJIWeSzPhyGQDtW" ,"id":"lgbt-9250_demigender"},{"body":"9412_progressflag","info":{"mimetype":"image/png","h":93, "w":128,"thumbnail_url":"mxc://matrix.org/cjxGMbeFSxhIELGaFOwSvknf"},"msgtype":"m.sticker","url":"mxc://matrix.org/cjxGMbeFSxhIELGaFOwSvknf" ,"id":"lgbt-9412_progressflag"}]}